netapult/__init__.py
netapult/channel.py
netapult/client.py
netapult/dispatch.py
netapult/exceptions.py
netapult/modes.py
netapult/types.py
netapult/util.py
netapult-0.0.1.dist-info/METADATA
netapult-0.0.1.dist-info/WHEEL
netapult-0.0.1.dist-info/entry_points.txt
netapult-0.0.1.dist-info/licenses/LICENSE
netapult-0.0.1.dist-info/RECORD
