Metadata-Version: 2.4
Name: netapult
Version: 0.0.1
Summary: Framework for terminal-based device management
Project-URL: Homepage, https://github.com/Jayson-Fong/netapult
Project-URL: Issues, https://github.com/Jayson-Fong/netapult/issues
Author-email: Jayson Fong <jayson.fong@gatech.edu>
License: MIT
License-File: LICENSE
Classifier: Development Status :: 1 - Planning
Classifier: License :: OSI Approved :: MIT License
Classifier: Operating System :: OS Independent
Classifier: Programming Language :: Python
Classifier: Programming Language :: Python :: 3.11
Classifier: Programming Language :: Python :: 3.12
Classifier: Programming Language :: Python :: 3.13
Classifier: Topic :: System :: Networking
Classifier: Typing :: Typed
Requires-Python: >=3.11
Provides-Extra: ssh
Requires-Dist: netapult-ssh==0.0.1; extra == 'ssh'
